xy_django_app_siteuser/__init__.py
xy_django_app_siteuser/abstracts.py
xy_django_app_siteuser/admin.py
xy_django_app_siteuser/apps.py
xy_django_app_siteuser/models.py
xy_django_app_siteuser/serializers.py
xy_django_app_siteuser/tests.py
xy_django_app_siteuser/views.py
xy_django_app_siteuser/migrations/__init__.py
xy_django_app_siteuser-1.0.3.dist-info/licenses/LICENSE
xy_django_app_siteuser-1.0.3.dist-info/METADATA
xy_django_app_siteuser-1.0.3.dist-info/WHEEL
xy_django_app_siteuser-1.0.3.dist-info/top_level.txt
xy_django_app_siteuser-1.0.3.dist-info/RECORD
