Metadata-Version: 2.4
Name: xy_django_app_siteuser
Version: 1.0.3
Summary: 站点用户数据模型
Author-email: 余洋 <yuyangit.0515@qq.com>
Classifier: Programming Language :: Python :: 3
Requires-Python: >=3.11.3
License-File: LICENSE
Requires-Dist: pytz
Requires-Dist: django
Requires-Dist: djangorestframework
Requires-Dist: pillow
Requires-Dist: xy_type
Requires-Dist: xy_string
Requires-Dist: xy_django_model
Requires-Dist: xy_django_serializer
Requires-Dist: xy_django_app_information
Dynamic: license-file
